session3/DictSession.py
session3/Session.py
session3/SessionManager.py
session3/__init__.py
session3/store/DirectorySessionStore.py
session3/store/DurusSessionStore.py
session3/store/MySQLSessionStore.py
session3/store/PostgresSessionStore.py
session3/store/SessionStore.py
session3/store/ShelveSessionStore.py
session3/store/VolatileSessionStore.py
session3/store/__init__.py
session3-3.4.1.dist-info/licenses/LICENSE
session3-3.4.1.dist-info/METADATA
session3-3.4.1.dist-info/WHEEL
session3-3.4.1.dist-info/top_level.txt
session3-3.4.1.dist-info/RECORD
