Metadata-Version: 2.4
Name: session3
Version: 3.4.1
Summary: Persistent sessions for Quixote 3
Home-page: http://www.file-away.co.uk/session3/README.html
Author: R J Ladyman [C. Titus Brown (titus@caltech.edu), and Mike Orr (mso@oz.net) for session2]
Author-email: it@file-away.co.uk
License: MIT
Platform: Most
Classifier: Programming Language :: Python :: 3 :: Only
Classifier: License :: OSI Approved :: MIT License
Classifier: Operating System :: OS Independent
Classifier: Development Status :: 5 - Production/Stable
Classifier: Intended Audience :: Developers
Classifier: Topic :: Internet :: WWW/HTTP :: Session
Requires-Python: >=3.9
License-File: LICENSE
Dynamic: author
Dynamic: author-email
Dynamic: classifier
Dynamic: description
Dynamic: description-content-type
Dynamic: home-page
Dynamic: license
Dynamic: license-file
Dynamic: platform
Dynamic: requires-python
Dynamic: summary
